pathao_api/__init__.py
pathao_api/cache.py
pathao_api/constants.py
pathao_api/controllers.py
pathao_api/core.py
pathao_api/routes.py
pathao_api/test.py
pathao_api-1.2.0.dist-info/METADATA
pathao_api-1.2.0.dist-info/WHEEL
pathao_api-1.2.0.dist-info/top_level.txt
pathao_api-1.2.0.dist-info/RECORD
