Metadata-Version: 2.4
Name: pathao-api
Version: 1.2.0
Summary: Unofficial Pathao API client for Python
Author-email: Muktadirul Islam Mahi <muktadirul.05@gmail.com>
License: MIT
Project-URL: Homepage, https://github.com/Muktadirul675/pathao-api
Requires-Python: >=3.7
Requires-Dist: requests>=2.28.0
Requires-Dist: python-dotenv>=1.0.0
